rocrateValidator/__init__.py
rocrateValidator/check_list.py
rocrateValidator/check_list.txt
rocrateValidator/semanticCheck.py
rocrateValidator/syntaxCheck.py
rocrateValidator/utils.py
rocrateValidator/validate.py
rocrateValidator/workflow_extension.py
rocrateValidator/workflow_extension.txt
rocrateValidator-0.2.15.dist-info/METADATA
rocrateValidator-0.2.15.dist-info/WHEEL
rocrateValidator-0.2.15.dist-info/top_level.txt
rocrateValidator-0.2.15.dist-info/RECORD
