Metadata-Version: 2.1
Name: rocrateValidator
Version: 0.2.15
Summary: This is python library for ro-crate validator
Home-page: https://github.com/ResearchObject/ro-crate-validator-py
License: UNKNOWN
Platform: UNKNOWN
